[{"Page":1,"Content":"leave \nblank\n2\n*p41802a0228*\n1. simplify\n7\n5\n5\n1\n+\n−\n \ngiving your answer in the form a\nb\n+\n5 , where a and b are integers.\n(4)\n\n\n\n\n\n\n\n\n\n\n\n\n\n\n\n\n\n\n\n\n\n\n\n\n\n\n\n\n\nq1\n(total 4 marks)\n","QP_Link":"https://qualifications.pearson.com/content/dam/pdf/A%20Level/Mathematics/2013/Exam%20materials/6663_01_que_20130513.pdf","MS_Link":"https://qualifications.pearson.com/content/dam/pdf/A%20Level/Mathematics/2013/Exam%20materials/6663_01_msc_20130815.pdf"},{"Page":2,"Content":"leave \nblank\n3\n*p41802a0328*\nturn over\n2. find\n∫\n√\n10\n4\n3\n4x\nx\nx\n−\n−\n⎛\n⎝⎜\n⎞\n⎠⎟\nx\nd\n \ngiving each term in its simplest form.\n(4)\n\n\n\n\n\n\n\n\n\n\n\n\n\n\n\n\n\n\n\n\n\n\n\n\n\n\n\n\n\nq2\n(total 4 marks)\n","QP_Link":"https://qualifications.pearson.com/content/dam/pdf/A%20Level/Mathematics/2013/Exam%20materials/6663_01_que_20130513.pdf","MS_Link":"https://qualifications.pearson.com/content/dam/pdf/A%20Level/Mathematics/2013/Exam%20materials/6663_01_msc_20130815.pdf"},{"Page":3,"Content":"leave \nblank\n4\n*p41802a0428*\n3. (a) find the value of 8\n5\n3\n(2)\n \n(b) simplify fully \n \n2\n4\n1\n2\n3\n2\nx\nx\n⎛\n⎝\n⎞\n⎠\n(3)\n\n\n\n\n\n\n\n\n\n\n\n\n\n\n\n\n\n\n\n\n\n\n\n\n\n\n\n\n\n\n\n","QP_Link":"https://qualifications.pearson.com/content/dam/pdf/A%20Level/Mathematics/2013/Exam%20materials/6663_01_que_20130513.pdf","MS_Link":"https://qualifications.pearson.com/content/dam/pdf/A%20Level/Mathematics/2013/Exam%20materials/6663_01_msc_20130815.pdf"},{"Page":4,"Content":"leave \nblank\n5\n*p41802a0528*\nturn over\nquestion 3 continued\n\n\n\n\n\n\n\n\n\n\n\n\n\n\n\n\n\n\n\n\n\n\n\n\n\n\n\n\n\n\n\n\n\n\nq3\n(total 5 marks)\n","QP_Link":"https://qualifications.pearson.com/content/dam/pdf/A%20Level/Mathematics/2013/Exam%20materials/6663_01_que_20130513.pdf","MS_Link":"https://qualifications.pearson.com/content/dam/pdf/A%20Level/Mathematics/2013/Exam%20materials/6663_01_msc_20130815.pdf"},{"Page":5,"Content":"leave \nblank\n6\n*p41802a0628*\n4. a sequence a1, a2, a3, ... is defined by\na1 = 4\nan +1 = k (an + 2),      for n \u0002 1\n \nwhere k is a constant.\n \n(a) find an expression for a2  in terms of k.\n(1)\n \ngiven that \nai\ni=∑\n=\n1\n3\n2,\n \n(b) find the two possible values of k.\n(6)\n\n\n\n\n\n\n\n\n\n\n\n\n\n\n\n\n\n\n\n\n\n\n\n\n\n","QP_Link":"https://qualifications.pearson.com/content/dam/pdf/A%20Level/Mathematics/2013/Exam%20materials/6663_01_que_20130513.pdf","MS_Link":"https://qualifications.pearson.com/content/dam/pdf/A%20Level/Mathematics/2013/Exam%20materials/6663_01_msc_20130815.pdf"},{"Page":6,"Content":"leave \nblank\n7\n*p41802a0728*\nturn over\nquestion 4 continued\n\n\n\n\n\n\n\n\n\n\n\n\n\n\n\n\n\n\n\n\n\n\n\n\n\n\n\n\n\n\n\n\n\n\nq4\n(total 7 marks)\n","QP_Link":"https://qualifications.pearson.com/content/dam/pdf/A%20Level/Mathematics/2013/Exam%20materials/6663_01_que_20130513.pdf","MS_Link":"https://qualifications.pearson.com/content/dam/pdf/A%20Level/Mathematics/2013/Exam%20materials/6663_01_msc_20130815.pdf"},{"Page":7,"Content":"leave \nblank\n8\n*p41802a0828*\n5. find the set of values of x for which\n \n(a) 2(3x + 4) > 1 – x\n(2)\n \n(b) 3x2 + 8x – 3 < 0\n(4)\n\n\n\n\n\n\n\n\n\n\n\n\n\n\n\n\n\n\n\n\n\n\n\n\n\n\n\n\n\n\n\n","QP_Link":"https://qualifications.pearson.com/content/dam/pdf/A%20Level/Mathematics/2013/Exam%20materials/6663_01_que_20130513.pdf","MS_Link":"https://qualifications.pearson.com/content/dam/pdf/A%20Level/Mathematics/2013/Exam%20materials/6663_01_msc_20130815.pdf"},{"Page":8,"Content":"leave \nblank\n9\n*p41802a0928*\nturn over\nquestion 5 continued\n\n\n\n\n\n\n\n\n\n\n\n\n\n\n\n\n\n\n\n\n\n\n\n\n\n\n\n\n\n\n\n\n\n\nq5\n(total 6 marks)\n","QP_Link":"https://qualifications.pearson.com/content/dam/pdf/A%20Level/Mathematics/2013/Exam%20materials/6663_01_que_20130513.pdf","MS_Link":"https://qualifications.pearson.com/content/dam/pdf/A%20Level/Mathematics/2013/Exam%20materials/6663_01_msc_20130815.pdf"},{"Page":9,"Content":"leave \nblank\n10\n*p41802a01028*\n6. the straight line l1 passes through the points (–1, 3) and (11, 12).\n \n(a) find an equation for l1 in the form ax + by + c = 0,\n \n \nwhere a, b and c are integers.\n(4)\n \nthe line l2 has equation  3y + 4x – 30 = 0.\n \n(b) find the coordinates of the point of intersection of l1  and l2 .\n(3)\n\n\n\n\n\n\n\n\n\n\n\n\n\n\n\n\n\n\n\n\n\n\n\n\n\n\n\n\n","QP_Link":"https://qualifications.pearson.com/content/dam/pdf/A%20Level/Mathematics/2013/Exam%20materials/6663_01_que_20130513.pdf","MS_Link":"https://qualifications.pearson.com/content/dam/pdf/A%20Level/Mathematics/2013/Exam%20materials/6663_01_msc_20130815.pdf"},{"Page":10,"Content":"leave \nblank\n11\n*p41802a01128*\nturn over\nquestion 6 continued\n\n\n\n\n\n\n\n\n\n\n\n\n\n\n\n\n\n\n\n\n\n\n\n\n\n\n\n\n\n\n\n\n\n\nq6\n(total 7 marks)\n","QP_Link":"https://qualifications.pearson.com/content/dam/pdf/A%20Level/Mathematics/2013/Exam%20materials/6663_01_que_20130513.pdf","MS_Link":"https://qualifications.pearson.com/content/dam/pdf/A%20Level/Mathematics/2013/Exam%20materials/6663_01_msc_20130815.pdf"},{"Page":11,"Content":"leave \nblank\n12\n*p41802a01228*\n7. a company, which is making 200 mobile phones each week, plans to increase its \nproduction. \n \nthe number of mobile phones produced is to be increased by 20 each week from 200 in \nweek 1 to 220 in week 2, to 240 in week 3 and so on, until it is producing 600 in week n. \n \n(a) find the value of n.\n(2)\n \nthe company then plans to continue to make 600 mobile phones each week.\n \n(b) find the total number of mobile phones that will be made in the first 52 weeks starting \nfrom and including week 1.\n(5)\n\n\n\n\n\n\n\n\n\n\n\n\n\n\n\n\n\n\n\n\n\n\n\n\n\n\n","QP_Link":"https://qualifications.pearson.com/content/dam/pdf/A%20Level/Mathematics/2013/Exam%20materials/6663_01_que_20130513.pdf","MS_Link":"https://qualifications.pearson.com/content/dam/pdf/A%20Level/Mathematics/2013/Exam%20materials/6663_01_msc_20130815.pdf"},{"Page":12,"Content":"leave \nblank\n13\n*p41802a01328*\nturn over\nquestion 7 continued\n\n\n\n\n\n\n\n\n\n\n\n\n\n\n\n\n\n\n\n\n\n\n\n\n\n\n\n\n\n\n\n\n\n\nq7\n(total 7 marks)\n","QP_Link":"https://qualifications.pearson.com/content/dam/pdf/A%20Level/Mathematics/2013/Exam%20materials/6663_01_que_20130513.pdf","MS_Link":"https://qualifications.pearson.com/content/dam/pdf/A%20Level/Mathematics/2013/Exam%20materials/6663_01_msc_20130815.pdf"},{"Page":13,"Content":"leave \nblank\n14\n*p41802a01428*\n8. \nfigure 1\n \nfigure 1 shows a sketch of the curve with equation y = f(x) where \nf(x) = (x + 3)2 (x – 1),      x \u0002\u0003\u0002.\n \nthe curve crosses the x-axis at (1, 0), touches it at (–3, 0) and crosses the y-axis at (0, –9) \n \n(a) in the space below, sketch the curve c with equation y = f(x + 2) and state the \ncoordinates of the points where the curve c meets the x-axis.\n(3)\n \n(b) write down an equation of the curve c.\n(1)\n \n(c) use your answer to part (b) to find the coordinates of the point where the curve c \nmeets the y-axis.\n(2)\ny\nx\n–9\n–3\n1\no\n","QP_Link":"https://qualifications.pearson.com/content/dam/pdf/A%20Level/Mathematics/2013/Exam%20materials/6663_01_que_20130513.pdf","MS_Link":"https://qualifications.pearson.com/content/dam/pdf/A%20Level/Mathematics/2013/Exam%20materials/6663_01_msc_20130815.pdf"},{"Page":14,"Content":"leave \nblank\n15\n*p41802a01528*\nturn over\nquestion 8 continued\n\n\n\n\n\n\n\n\n\n\n\n\n\n\n\n\n\n\n\n\n\n\n\n\n\n\n\n\n\n\n\n\n\n\n\n","QP_Link":"https://qualifications.pearson.com/content/dam/pdf/A%20Level/Mathematics/2013/Exam%20materials/6663_01_que_20130513.pdf","MS_Link":"https://qualifications.pearson.com/content/dam/pdf/A%20Level/Mathematics/2013/Exam%20materials/6663_01_msc_20130815.pdf"},{"Page":15,"Content":"leave \nblank\n16\n*p41802a01628*\nquestion 8 continued\n\n\n\n\n\n\n\n\n\n\n\n\n\n\n\n\n\n\n\n\n\n\n\n\n\n\n\n\n\n\n\n\n\n\n\n","QP_Link":"https://qualifications.pearson.com/content/dam/pdf/A%20Level/Mathematics/2013/Exam%20materials/6663_01_que_20130513.pdf","MS_Link":"https://qualifications.pearson.com/content/dam/pdf/A%20Level/Mathematics/2013/Exam%20materials/6663_01_msc_20130815.pdf"},{"Page":16,"Content":"leave \nblank\n17\n*p41802a01728*\nturn over\nquestion 8 continued\nq8\n(total 6 marks)\n","QP_Link":"https://qualifications.pearson.com/content/dam/pdf/A%20Level/Mathematics/2013/Exam%20materials/6663_01_que_20130513.pdf","MS_Link":"https://qualifications.pearson.com/content/dam/pdf/A%20Level/Mathematics/2013/Exam%20materials/6663_01_msc_20130815.pdf"},{"Page":17,"Content":"leave \nblank\n18\n*p41802a01828*\n9. \nf'( )\n(\n) ,\nx\nx\nx\nx\n=\n−\n≠\n3\n0\n2\n2\n2\n \n(a) show that \nf'(x) = 9x–2 + a + bx2,\n \nwhere a and b are constants to be found.\n(3)\n \n(b) find f\"(x).\n(2)\n \ngiven that the point (–3, 10) lies on the curve with equation y = f (x),\n \n(c) find f (x).\n(5)\n\n\n\n\n\n\n\n\n\n\n\n\n\n\n\n\n\n\n\n\n\n\n\n\n","QP_Link":"https://qualifications.pearson.com/content/dam/pdf/A%20Level/Mathematics/2013/Exam%20materials/6663_01_que_20130513.pdf","MS_Link":"https://qualifications.pearson.com/content/dam/pdf/A%20Level/Mathematics/2013/Exam%20materials/6663_01_msc_20130815.pdf"},{"Page":18,"Content":"leave \nblank\n19\n*p41802a01928*\nturn over\nquestion 9 continued\n\n\n\n\n\n\n\n\n\n\n\n\n\n\n\n\n\n\n\n\n\n\n\n\n\n\n\n\n\n\n\n\n\n\nq9\n(total 10 marks)\n","QP_Link":"https://qualifications.pearson.com/content/dam/pdf/A%20Level/Mathematics/2013/Exam%20materials/6663_01_que_20130513.pdf","MS_Link":"https://qualifications.pearson.com/content/dam/pdf/A%20Level/Mathematics/2013/Exam%20materials/6663_01_msc_20130815.pdf"},{"Page":19,"Content":"leave \nblank\n20\n*p41802a02028*\n10. given the simultaneous equations\n \n2x + y = 1\n \nx2 – 4ky + 5k = 0\n \nwhere k is a non zero constant,\n \n(a) show that\nx2 + 8kx + k = 0\n(2)\n \ngiven that x2 + 8kx + k = 0 has equal roots,\n \n(b) find the value of k.\n(3)\n \n(c) for this value of k, find the solution of the simultaneous equations.\n(3)\n\n\n\n\n\n\n\n\n\n\n\n\n\n\n\n\n\n\n\n\n\n\n","QP_Link":"https://qualifications.pearson.com/content/dam/pdf/A%20Level/Mathematics/2013/Exam%20materials/6663_01_que_20130513.pdf","MS_Link":"https://qualifications.pearson.com/content/dam/pdf/A%20Level/Mathematics/2013/Exam%20materials/6663_01_msc_20130815.pdf"},{"Page":20,"Content":"leave \nblank\n21\n*p41802a02128*\nturn over\nquestion 10 continued\n\n\n\n\n\n\n\n\n\n\n\n\n\n\n\n\n\n\n\n\n\n\n\n\n\n\n\n\n\n\n\n\n\n\n\n","QP_Link":"https://qualifications.pearson.com/content/dam/pdf/A%20Level/Mathematics/2013/Exam%20materials/6663_01_que_20130513.pdf","MS_Link":"https://qualifications.pearson.com/content/dam/pdf/A%20Level/Mathematics/2013/Exam%20materials/6663_01_msc_20130815.pdf"},{"Page":21,"Content":"leave \nblank\n22\n*p41802a02228*\nquestion 10 continued\n\n\n\n\n\n\n\n\n\n\n\n\n\n\n\n\n\n\n\n\n\n\n\n\n\n\n\n\n\n\n\n\n\n\n\n","QP_Link":"https://qualifications.pearson.com/content/dam/pdf/A%20Level/Mathematics/2013/Exam%20materials/6663_01_que_20130513.pdf","MS_Link":"https://qualifications.pearson.com/content/dam/pdf/A%20Level/Mathematics/2013/Exam%20materials/6663_01_msc_20130815.pdf"},{"Page":22,"Content":"leave \nblank\n23\n*p41802a02328*\nturn over\nquestion 10 continued\n\n\n\n\n\n\n\n\n\n\n\n\n\n\n\n\n\n\n\n\n\n\n\n\n\n\n\n\n\n\n\n\n\n\nq10\n(total 8 marks)\n","QP_Link":"https://qualifications.pearson.com/content/dam/pdf/A%20Level/Mathematics/2013/Exam%20materials/6663_01_que_20130513.pdf","MS_Link":"https://qualifications.pearson.com/content/dam/pdf/A%20Level/Mathematics/2013/Exam%20materials/6663_01_msc_20130815.pdf"},{"Page":23,"Content":"leave \nblank\n24\n*p41802a02428*\n11.\nfigure 2\n \nfigure 2 shows a sketch of the curve h with equation y\nx\n=\n+\n3\n4 ,  x\u0002\u0003\u0002\u0004\u0005\n \n(a) give the coordinates of the point where h crosses the x-axis.\n(1)\n \n(b) give the equations of the asymptotes to h.\n(2)\n \n(c) find an equation for the normal to h at the point p(–3, 3).\n(5)\n \nthis normal crosses the x-axis at a and the y-axis at b.\n \n(d) find the length of the line segment ab.  give your answer as a surd.\n(3)\n\n\n\n\n\n\n\n\n\n\n\n\n\ny\nx\no\n","QP_Link":"https://qualifications.pearson.com/content/dam/pdf/A%20Level/Mathematics/2013/Exam%20materials/6663_01_que_20130513.pdf","MS_Link":"https://qualifications.pearson.com/content/dam/pdf/A%20Level/Mathematics/2013/Exam%20materials/6663_01_msc_20130815.pdf"},{"Page":24,"Content":"leave \nblank\n25\n*p41802a02528*\nturn over\nquestion 11 continued\n\n\n\n\n\n\n\n\n\n\n\n\n\n\n\n\n\n\n\n\n\n\n\n\n\n\n\n\n\n\n\n\n\n\n\n","QP_Link":"https://qualifications.pearson.com/content/dam/pdf/A%20Level/Mathematics/2013/Exam%20materials/6663_01_que_20130513.pdf","MS_Link":"https://qualifications.pearson.com/content/dam/pdf/A%20Level/Mathematics/2013/Exam%20materials/6663_01_msc_20130815.pdf"},{"Page":25,"Content":"leave \nblank\n26\n*p41802a02628*\nquestion 11 continued\n\n\n\n\n\n\n\n\n\n\n\n\n\n\n\n\n\n\n\n\n\n\n\n\n\n\n\n\n\n\n\n\n\n\n\n","QP_Link":"https://qualifications.pearson.com/content/dam/pdf/A%20Level/Mathematics/2013/Exam%20materials/6663_01_que_20130513.pdf","MS_Link":"https://qualifications.pearson.com/content/dam/pdf/A%20Level/Mathematics/2013/Exam%20materials/6663_01_msc_20130815.pdf"},{"Page":26,"Content":"leave \nblank\n27\n*p41802a02728*\nturn over\nquestion 11 continued\n\n\n\n\n\n\n\n\n\n\n\n\n\n\n\n\n\n\n\n\n\n\n\n\n\n\n\n\n\n\n\n\n\n\n\n","QP_Link":"https://qualifications.pearson.com/content/dam/pdf/A%20Level/Mathematics/2013/Exam%20materials/6663_01_que_20130513.pdf","MS_Link":"https://qualifications.pearson.com/content/dam/pdf/A%20Level/Mathematics/2013/Exam%20materials/6663_01_msc_20130815.pdf"},{"Page":27,"Content":"leave \nblank\n28\n*p41802a02828*\nquestion 11 continued\n\n\n\n\n\n\n\n\n\n\n\n\n\n\n\n\n\n\n\n\n\n\n\n\n\n\n\n\n\n\n\n\ntotal for paper: 75 marks\nend\nq11\n(total 11 marks)\n","QP_Link":"https://qualifications.pearson.com/content/dam/pdf/A%20Level/Mathematics/2013/Exam%20materials/6663_01_que_20130513.pdf","MS_Link":"https://qualifications.pearson.com/content/dam/pdf/A%20Level/Mathematics/2013/Exam%20materials/6663_01_msc_20130815.pdf"}]