[{"Page":1,"Content":"leave \nblank\n2\n*n26319a0228*\n1. solve the differential equation\nd\nd\ny\nx\ny\nx\n−\n=\n3\n \nto obtain y as a function of x.\n(5)\n\n\n\n\n\n\n\n\n\n\n\n\n\n\n\n\n\n\n\n\n\n\n\n\n\n\n\n\n\n \n\n","QP_Link":"https://qualifications.pearson.com/content/dam/pdf/A%20Level/Mathematics/2013/Exam%20materials/6674_01_que_20080130.pdf","MS_Link":"https://qualifications.pearson.com/content/dam/pdf/A%20Level/Mathematics/2013/Exam%20materials/6674_01_rms_20080306.pdf"},{"Page":2,"Content":"leave \nblank\n3\nturn over\n*n26319a0328*\nquestion 1 continued\n\n\n\n\n\n\n\n\n\n\n\n\n\n\n\n\n\n\n\n\n\n\n\n\n\n\n\n\n\n\n\n\n\n\nq1\n(total 5 marks)\n","QP_Link":"https://qualifications.pearson.com/content/dam/pdf/A%20Level/Mathematics/2013/Exam%20materials/6674_01_que_20080130.pdf","MS_Link":"https://qualifications.pearson.com/content/dam/pdf/A%20Level/Mathematics/2013/Exam%20materials/6674_01_rms_20080306.pdf"},{"Page":3,"Content":"leave \nblank\n4\n*n26319a0428*\n2. given that x = −1\n2  is the real solution of the equation\n2\n11\n14\n10\n0\n3\n2\nx\nx\nx\n−\n+\n+\n= ,\n \nfind the two complex solutions of this equation.\n(6)\n\n\n\n\n\n\n\n\n\n\n\n\n\n\n\n\n\n\n\n\n\n\n\n\n\n\n\n\n\n\n\n","QP_Link":"https://qualifications.pearson.com/content/dam/pdf/A%20Level/Mathematics/2013/Exam%20materials/6674_01_que_20080130.pdf","MS_Link":"https://qualifications.pearson.com/content/dam/pdf/A%20Level/Mathematics/2013/Exam%20materials/6674_01_rms_20080306.pdf"},{"Page":4,"Content":"leave \nblank\n5\nturn over\n*n26319a0528*\nquestion 2 continued\n\n\n\n\n\n\n\n\n\n\n\n\n\n\n\n\n\n\n\n\n\n\n\n\n\n\n\n\n\n\n\n\n\n\nq2\n(total 6 marks)\n","QP_Link":"https://qualifications.pearson.com/content/dam/pdf/A%20Level/Mathematics/2013/Exam%20materials/6674_01_que_20080130.pdf","MS_Link":"https://qualifications.pearson.com/content/dam/pdf/A%20Level/Mathematics/2013/Exam%20materials/6674_01_rms_20080306.pdf"},{"Page":5,"Content":"leave \nblank\n6\n*n26319a0628*\n3. (a) simplify the expression (\n)(\n)\n(\n),\nx\nx\nx\nx\n+\n+\n−\n−\n−\n3\n9\n1\n3\n5  giving your answer in the form\n             a x\nb x\nc\nx\n(\n)(\n) ,\n+\n+\n−1\n where a, b and c are integers.\n(4)\n \n(b) hence, or otherwise, solve the inequality\n(\n)(\n)\n.\nx\nx\nx\nx\n+\n+\n−\n>\n−\n3\n9\n1\n3\n5\n(4)\n\n\n\n\n\n\n\n\n\n\n\n\n\n\n\n\n\n\n\n\n\n\n\n\n\n\n\n","QP_Link":"https://qualifications.pearson.com/content/dam/pdf/A%20Level/Mathematics/2013/Exam%20materials/6674_01_que_20080130.pdf","MS_Link":"https://qualifications.pearson.com/content/dam/pdf/A%20Level/Mathematics/2013/Exam%20materials/6674_01_rms_20080306.pdf"},{"Page":6,"Content":"leave \nblank\n7\nturn over\n*n26319a0728*\nquestion 3 continued\n\n\n\n\n\n\n\n\n\n\n\n\n\n\n\n\n\n\n\n\n\n\n\n\n\n\n\n\n\n\n\n\n\n\n\n","QP_Link":"https://qualifications.pearson.com/content/dam/pdf/A%20Level/Mathematics/2013/Exam%20materials/6674_01_que_20080130.pdf","MS_Link":"https://qualifications.pearson.com/content/dam/pdf/A%20Level/Mathematics/2013/Exam%20materials/6674_01_rms_20080306.pdf"},{"Page":7,"Content":"leave \nblank\n8\n*n26319a0828*\nquestion 3 continued\n\n\n\n\n\n\n\n\n\n\n\n\n\n\n\n\n\n\n\n\n\n\n\n\n\n\n\n\n\n\n\n\n\n\n\n","QP_Link":"https://qualifications.pearson.com/content/dam/pdf/A%20Level/Mathematics/2013/Exam%20materials/6674_01_que_20080130.pdf","MS_Link":"https://qualifications.pearson.com/content/dam/pdf/A%20Level/Mathematics/2013/Exam%20materials/6674_01_rms_20080306.pdf"},{"Page":8,"Content":"leave \nblank\n9\nturn over\n*n26319a0928*\nq3\n(total 8 marks)\nquestion 3 continued\n\n\n\n\n\n\n\n\n\n\n\n\n\n\n\n\n\n\n\n\n\n\n\n\n\n\n\n\n\n\n\n\n\n\n","QP_Link":"https://qualifications.pearson.com/content/dam/pdf/A%20Level/Mathematics/2013/Exam%20materials/6674_01_que_20080130.pdf","MS_Link":"https://qualifications.pearson.com/content/dam/pdf/A%20Level/Mathematics/2013/Exam%20materials/6674_01_rms_20080306.pdf"},{"Page":9,"Content":"leave \nblank\n10\n*n26319a01028*\n4.\nf ( )\ntan\n,\n.\nx\nx\nx\nx\nx\n=\n+\n−\n\n\n\n−\n−\n<\n<\n3\n2\n2\n2\nπ\nπ\n \nthe equation f(x) = 0 has a root α in the interval [0.7, 0.8].\n \n(a) use linear interpolation, on the values at the end points of this interval, to obtain an \napproximation to α.  give your answer to 3 decimal places.\n(4)\n \n(b) taking 0.75 as a first approximation to α, apply the newton–raphson procedure \nonce to f(x)  to obtain a second approximation to α.  give your answer to 3 decimal \nplaces.\n(4)\n\n\n\n\n\n\n\n\n\n\n\n\n\n\n\n\n\n\n\n\n\n\n\n\n\n\n","QP_Link":"https://qualifications.pearson.com/content/dam/pdf/A%20Level/Mathematics/2013/Exam%20materials/6674_01_que_20080130.pdf","MS_Link":"https://qualifications.pearson.com/content/dam/pdf/A%20Level/Mathematics/2013/Exam%20materials/6674_01_rms_20080306.pdf"},{"Page":10,"Content":"leave \nblank\n11\nturn over\n*n26319a01128*\nquestion 4 continued\n\n\n\n\n\n\n\n\n\n\n\n\n\n\n\n\n\n\n\n\n\n\n\n\n\n\n\n\n\n\n\n\n\n\nq4\n(total 8 marks)\n","QP_Link":"https://qualifications.pearson.com/content/dam/pdf/A%20Level/Mathematics/2013/Exam%20materials/6674_01_que_20080130.pdf","MS_Link":"https://qualifications.pearson.com/content/dam/pdf/A%20Level/Mathematics/2013/Exam%20materials/6674_01_rms_20080306.pdf"},{"Page":11,"Content":"leave \nblank\n12\n*n26319a01228*\n5. (a)  express \n5\n4\n1\n2\nr\nr r\nr\n+\n+\n+\n(\n)(\n)  in partial fractions.\n(4)\n \n(b) hence, or otherwise, show that\n                                                 \n5\n4\n1\n2\n7\n11\n2\n1\n2\n1\n2\nr\nr r\nr\nn\nn\nn\nn\nr\nn\n+\n+\n+\n=\n+\n+\n+\n=∑(\n)(\n)\n(\n)(\n) .\n(5)\n\n\n\n\n\n\n\n\n\n\n\n\n\n\n\n\n\n\n\n\n\n\n\n\n\n\n\n\n\n","QP_Link":"https://qualifications.pearson.com/content/dam/pdf/A%20Level/Mathematics/2013/Exam%20materials/6674_01_que_20080130.pdf","MS_Link":"https://qualifications.pearson.com/content/dam/pdf/A%20Level/Mathematics/2013/Exam%20materials/6674_01_rms_20080306.pdf"},{"Page":12,"Content":"leave \nblank\n13\nturn over\n*n26319a01328*\nquestion 5 continued\n\n\n\n\n\n\n\n\n\n\n\n\n\n\n\n\n\n\n\n\n\n\n\n\n\n\n\n\n\n\n\n\n\n\n\n","QP_Link":"https://qualifications.pearson.com/content/dam/pdf/A%20Level/Mathematics/2013/Exam%20materials/6674_01_que_20080130.pdf","MS_Link":"https://qualifications.pearson.com/content/dam/pdf/A%20Level/Mathematics/2013/Exam%20materials/6674_01_rms_20080306.pdf"},{"Page":13,"Content":"leave \nblank\n14\n*n26319a01428*\nquestion 5 continued\n\n\n\n\n\n\n\n\n\n\n\n\n\n\n\n\n\n\n\n\n\n\n\n\n\n\n\n\n\n\n\n\n\n\n\n","QP_Link":"https://qualifications.pearson.com/content/dam/pdf/A%20Level/Mathematics/2013/Exam%20materials/6674_01_que_20080130.pdf","MS_Link":"https://qualifications.pearson.com/content/dam/pdf/A%20Level/Mathematics/2013/Exam%20materials/6674_01_rms_20080306.pdf"},{"Page":14,"Content":"leave \nblank\n15\nturn over\n*n26319a01528*\nquestion 5 continued\n\n\n\n\n\n\n\n\n\n\n\n\n\n\n\n\n\n\n\n\n\n\n\n\n\n\n\n\n\n\n\n\n\n\nq5\n(total 9 marks)\n","QP_Link":"https://qualifications.pearson.com/content/dam/pdf/A%20Level/Mathematics/2013/Exam%20materials/6674_01_que_20080130.pdf","MS_Link":"https://qualifications.pearson.com/content/dam/pdf/A%20Level/Mathematics/2013/Exam%20materials/6674_01_rms_20080306.pdf"},{"Page":15,"Content":"leave \nblank\n16\n*n26319a01628*\n6. \nz = −+\n2\ni.\n \n(a) express in the form a + ib\n \n \n(i)   1\nz ,\n \n \n(ii)   z2.\n(4)\n \n(b) show that  z\nz\n2\n5\n−\n= √2.\n(2)\n \n(c) find arg (z2  – z ).\n(2)\n \n(d) display z and z2  – z on a single argand diagram.\n(2)\n\n\n\n\n\n\n\n\n\n\n\n\n\n\n\n\n\n\n\n\n\n\n\n\n","QP_Link":"https://qualifications.pearson.com/content/dam/pdf/A%20Level/Mathematics/2013/Exam%20materials/6674_01_que_20080130.pdf","MS_Link":"https://qualifications.pearson.com/content/dam/pdf/A%20Level/Mathematics/2013/Exam%20materials/6674_01_rms_20080306.pdf"},{"Page":16,"Content":"leave \nblank\n17\nturn over\n*n26319a01728*\nquestion 6 continued\n\n\n\n\n\n\n\n\n\n\n\n\n\n\n\n\n\n\n\n\n\n\n\n\n\n\n\n\n\n\n\n\n\n\n\n","QP_Link":"https://qualifications.pearson.com/content/dam/pdf/A%20Level/Mathematics/2013/Exam%20materials/6674_01_que_20080130.pdf","MS_Link":"https://qualifications.pearson.com/content/dam/pdf/A%20Level/Mathematics/2013/Exam%20materials/6674_01_rms_20080306.pdf"},{"Page":17,"Content":"leave \nblank\n18\n*n26319a01828*\nquestion 6 continued\n\n\n\n\n\n\n\n\n\n\n\n\n\n\n\n\n\n\n\n\n\n\n\n\n\n\n\n\n\n\n\n\n\n\n\n","QP_Link":"https://qualifications.pearson.com/content/dam/pdf/A%20Level/Mathematics/2013/Exam%20materials/6674_01_que_20080130.pdf","MS_Link":"https://qualifications.pearson.com/content/dam/pdf/A%20Level/Mathematics/2013/Exam%20materials/6674_01_rms_20080306.pdf"},{"Page":18,"Content":"leave \nblank\n19\nturn over\n*n26319a01928*\nquestion 6 continued\n\n\n\n\n\n\n\n\n\n\n\n\n\n\n\n\n\n\n\n\n\n\n\n\n\n\n\n\n\n\n\n\n\n\nq6\n(total 10 marks)\n","QP_Link":"https://qualifications.pearson.com/content/dam/pdf/A%20Level/Mathematics/2013/Exam%20materials/6674_01_que_20080130.pdf","MS_Link":"https://qualifications.pearson.com/content/dam/pdf/A%20Level/Mathematics/2013/Exam%20materials/6674_01_rms_20080306.pdf"},{"Page":19,"Content":"leave \nblank\n20\n*n26319a02028*\n7. (a) find the general solution of the differential equation\n                                                           3\n2\n2\n2\n2\nd\nd\nd\nd\ny\nx\ny\nx\ny\nx\n−\n−\n=\n.\n(8)\n \n(b) find the particular solution for which, at \nand d\nd\nx\ny\ny\nx\n=\n=\n=\n0\n2\n3\n,\n.\n(6)\n\n\n\n\n\n\n\n\n\n\n\n\n\n\n\n\n\n\n\n\n\n\n\n\n\n\n\n\n\n","QP_Link":"https://qualifications.pearson.com/content/dam/pdf/A%20Level/Mathematics/2013/Exam%20materials/6674_01_que_20080130.pdf","MS_Link":"https://qualifications.pearson.com/content/dam/pdf/A%20Level/Mathematics/2013/Exam%20materials/6674_01_rms_20080306.pdf"},{"Page":20,"Content":"leave \nblank\n21\nturn over\n*n26319a02128*\nquestion 7 continued\n\n\n\n\n\n\n\n\n\n\n\n\n\n\n\n\n\n\n\n\n\n\n\n\n\n\n\n\n\n\n\n\n\n\n\n","QP_Link":"https://qualifications.pearson.com/content/dam/pdf/A%20Level/Mathematics/2013/Exam%20materials/6674_01_que_20080130.pdf","MS_Link":"https://qualifications.pearson.com/content/dam/pdf/A%20Level/Mathematics/2013/Exam%20materials/6674_01_rms_20080306.pdf"},{"Page":21,"Content":"leave \nblank\n22\n*n26319a02228*\nquestion 7 continued\n\n\n\n\n\n\n\n\n\n\n\n\n\n\n\n\n\n\n\n\n\n\n\n\n\n\n\n\n\n\n\n\n\n\n\n","QP_Link":"https://qualifications.pearson.com/content/dam/pdf/A%20Level/Mathematics/2013/Exam%20materials/6674_01_que_20080130.pdf","MS_Link":"https://qualifications.pearson.com/content/dam/pdf/A%20Level/Mathematics/2013/Exam%20materials/6674_01_rms_20080306.pdf"},{"Page":22,"Content":"leave \nblank\n23\nturn over\n*n26319a02328*\nquestion 7 continued\n\n\n\n\n\n\n\n\n\n\n\n\n\n\n\n\n\n\n\n\n\n\n\n\n\n\n\n\n\n\n\n\n\n\nq7\n(total 14 marks)\n","QP_Link":"https://qualifications.pearson.com/content/dam/pdf/A%20Level/Mathematics/2013/Exam%20materials/6674_01_que_20080130.pdf","MS_Link":"https://qualifications.pearson.com/content/dam/pdf/A%20Level/Mathematics/2013/Exam%20materials/6674_01_rms_20080306.pdf"},{"Page":23,"Content":"leave \nblank\n24\n*n26319a02428*\n8. \nfigure 1\n \nfigure 1 shows the curve c1 which has polar equation r = a(3 + 2cosθ), 0 - θ < 2π, and \nthe circle c2 with equation r = 4a, 0 - θ < 2π,  where a is a positive constant.\n \n(a) find, in terms of a, the polar coordinates of the points where the curve c1 meets the \ncircle c2.\n(4)\n \nthe regions enclosed by the curves c1 and c2 overlap and this common region r is shaded \nin the figure.\n \n(b) find, in terms of a, an exact expression for the area of the shaded region r.\n(8)\n \n(c) in a single diagram, copy the two curves in figure 1 and also sketch the curve c3 with \npolar equation r = 2a cos θ, 0 - θ < 2π.  show clearly the coordinates of the points of \nintersection of c1, c2 and c3 with the initial line, θ = 0.\n(3)\n\n\n\n\n\n\n\n\n\n\n\n\n\n\nθ = 0\nc2\nc1\no\n","QP_Link":"https://qualifications.pearson.com/content/dam/pdf/A%20Level/Mathematics/2013/Exam%20materials/6674_01_que_20080130.pdf","MS_Link":"https://qualifications.pearson.com/content/dam/pdf/A%20Level/Mathematics/2013/Exam%20materials/6674_01_rms_20080306.pdf"},{"Page":24,"Content":"leave \nblank\n25\nturn over\n*n26319a02528*\nquestion 8 continued\n\n\n\n\n\n\n\n\n\n\n\n\n\n\n\n\n\n\n\n\n\n\n\n\n\n\n\n\n\n\n\n\n\n\n\n","QP_Link":"https://qualifications.pearson.com/content/dam/pdf/A%20Level/Mathematics/2013/Exam%20materials/6674_01_que_20080130.pdf","MS_Link":"https://qualifications.pearson.com/content/dam/pdf/A%20Level/Mathematics/2013/Exam%20materials/6674_01_rms_20080306.pdf"},{"Page":25,"Content":"leave \nblank\n26\n*n26319a02628*\nquestion 8 continued\n\n\n\n\n\n\n\n\n\n\n\n\n\n\n\n\n\n\n\n\n\n\n\n\n\n\n\n\n\n\n\n\n\n\n\n","QP_Link":"https://qualifications.pearson.com/content/dam/pdf/A%20Level/Mathematics/2013/Exam%20materials/6674_01_que_20080130.pdf","MS_Link":"https://qualifications.pearson.com/content/dam/pdf/A%20Level/Mathematics/2013/Exam%20materials/6674_01_rms_20080306.pdf"},{"Page":26,"Content":"leave \nblank\n27\n*n26319a02728*\nquestion 8 continued\n\n\n\n\n\n\n\n\n\n\n\n\n\n\n\n\n\n\n\n\n\n\n\n\n\n\n\n\n\n\n\n\ntotal for paper: 75 marks\nend\nq8\n(total 15 marks)\n","QP_Link":"https://qualifications.pearson.com/content/dam/pdf/A%20Level/Mathematics/2013/Exam%20materials/6674_01_que_20080130.pdf","MS_Link":"https://qualifications.pearson.com/content/dam/pdf/A%20Level/Mathematics/2013/Exam%20materials/6674_01_rms_20080306.pdf"},{"Page":27,"Content":"28\n*n26319a02828*\nblank page\n","QP_Link":"https://qualifications.pearson.com/content/dam/pdf/A%20Level/Mathematics/2013/Exam%20materials/6674_01_que_20080130.pdf","MS_Link":"https://qualifications.pearson.com/content/dam/pdf/A%20Level/Mathematics/2013/Exam%20materials/6674_01_rms_20080306.pdf"}]